lopt/__init__.py
lopt/errors.py
lopt/formatter.py
lopt/models.py
lopt/parser.py
lopt/py.typed
llm_opt-0.1.4.dist-info/METADATA
llm_opt-0.1.4.dist-info/WHEEL
llm_opt-0.1.4.dist-info/RECORD
